mupa_client.py
mupa_client-0.1.0.dist-info/WHEEL
mupa_client-0.1.0.dist-info/METADATA
mupa_client-0.1.0.dist-info/RECORD
